h_matchers/__init__.py
h_matchers/decorator.py
h_matchers/exception.py
h_matchers/interface.py
h_matchers/matcher/__init__.py
h_matchers/matcher/anything.py
h_matchers/matcher/combination.py
h_matchers/matcher/core.py
h_matchers/matcher/meta.py
h_matchers/matcher/number.py
h_matchers/matcher/object.py
h_matchers/matcher/strings.py
h_matchers/matcher/collection/__init__.py
h_matchers/matcher/collection/containment.py
h_matchers/matcher/collection/_mixin/__init__.py
h_matchers/matcher/collection/_mixin/contains.py
h_matchers/matcher/collection/_mixin/item_matcher.py
h_matchers/matcher/collection/_mixin/size.py
h_matchers/matcher/collection/_mixin/type.py
h_matchers/matcher/web/__init__.py
h_matchers/matcher/web/request.py
h_matchers/matcher/web/url/__init__.py
h_matchers/matcher/web/url/core.py
h_matchers/matcher/web/url/fluent.py
h_matchers-1.2.17.dist-info/LICENSE
h_matchers-1.2.17.dist-info/METADATA
h_matchers-1.2.17.dist-info/WHEEL
h_matchers-1.2.17.dist-info/top_level.txt
h_matchers-1.2.17.dist-info/RECORD
