Metadata-Version: 2.2
Name: h-matchers
Version: 1.2.17
Summary: Test objects which pass equality checks with other objects.
Home-page: https://github.com/hypothesis/h-matchers
Project-URL: Bug Tracker, https://github.com/hypothesis/h-matchers/issues
Project-URL: Changelog, https://github.com/hypothesis/h-matchers/releases
Classifier: Programming Language :: Python :: 3
Classifier: License :: OSI Approved :: BSD License
Classifier: Intended Audience :: Developers
Requires-Python: >=3.9
License-File: LICENSE
